<?xml version='1.0' encoding='UTF-8'?>
<?artifactRepository version='1.1.0'?>
<repository name='file:/C:/Users/Andy/Documents/GitHub/mule-xero-connector/target/update-site/ - artifacts' type='org.eclipse.equinox.p2.artifact.repository.simpleRepository' version='1'>
  <properties size='2'>
    <property name='p2.timestamp' value='1363691912268'/>
    <property name='p2.compressed' value='false'/>
  </properties>
  <mappings size='3'>
    <rule filter='(&amp; (classifier=osgi.bundle))' output='${repoUrl}/plugins/${id}_${version}.jar'/>
    <rule filter='(&amp; (classifier=binary))' output='${repoUrl}/binary/${id}_${version}'/>
    <rule filter='(&amp; (classifier=org.eclipse.update.feature))' output='${repoUrl}/features/${id}_${version}.jar'/>
  </mappings>
  <artifacts size='2'>
    <artifact classifier='osgi.bundle' id='org.mule.tooling.ui.extension.xero' version='1.0.0.201303192218'>
      <properties size='3'>
        <property name='artifact.size' value='1442952'/>
        <property name='download.size' value='1442952'/>
        <property name='download.md5' value='b2656bf37fc153b9a088f0eda786aa20'/>
      </properties>
    </artifact>
    <artifact classifier='org.eclipse.update.feature' id='org.mule.tooling.ui.extension.xero' version='1.0.0.201303192218'>
      <properties size='4'>
        <property name='artifact.size' value='635'/>
        <property name='download.size' value='635'/>
        <property name='download.md5' value='41274a960e6fe810b573a963d15d2593'/>
        <property name='download.contentType' value='application/zip'/>
      </properties>
    </artifact>
  </artifacts>
</repository>
